{"nodes": [{"id": "f_youtube_2_0_src_content_features_player_mini_player_js", "label": "mini-player.js", "file_type": "code", "source_file": "F:\\Youtube 2.0\\src\\content\\features\\player\\mini-player.js", "source_location": "L1"}, {"id": "player_mini_player_constructor", "label": "constructor()", "file_type": "code", "source_file": "F:\\Youtube 2.0\\src\\content\\features\\player\\mini-player.js", "source_location": "L9"}, {"id": "player_mini_player_getconfigkey", "label": "getConfigKey()", "file_type": "code", "source_file": "F:\\Youtube 2.0\\src\\content\\features\\player\\mini-player.js", "source_location": "L30"}, {"id": "player_mini_player_enable", "label": "enable()", "file_type": "code", "source_file": "F:\\Youtube 2.0\\src\\content\\features\\player\\mini-player.js", "source_location": "L34"}, {"id": "player_mini_player_disable", "label": "disable()", "file_type": "code", "source_file": "F:\\Youtube 2.0\\src\\content\\features\\player\\mini-player.js", "source_location": "L50"}, {"id": "player_mini_player_checkminiplayerstate", "label": "checkMiniplayerState()", "file_type": "code", "source_file": "F:\\Youtube 2.0\\src\\content\\features\\player\\mini-player.js", "source_location": "L66"}, {"id": "player_mini_player_injectresizehandle", "label": "injectResizeHandle()", "file_type": "code", "source_file": "F:\\Youtube 2.0\\src\\content\\features\\player\\mini-player.js", "source_location": "L82"}, {"id": "player_mini_player_ondragstart", "label": "onDragStart()", "file_type": "code", "source_file": "F:\\Youtube 2.0\\src\\content\\features\\player\\mini-player.js", "source_location": "L113"}, {"id": "player_mini_player_ondrag", "label": "onDrag()", "file_type": "code", "source_file": "F:\\Youtube 2.0\\src\\content\\features\\player\\mini-player.js", "source_location": "L132"}, {"id": "player_mini_player_ondragend", "label": "onDragEnd()", "file_type": "code", "source_file": "F:\\Youtube 2.0\\src\\content\\features\\player\\mini-player.js", "source_location": "L154"}], "edges": [{"source": "f_youtube_2_0_src_content_features_player_mini_player_js", "target": "player_mini_player_constructor", "relation": "contains", "confidence": "EXTRACTED", "source_file": "F:\\Youtube 2.0\\src\\content\\features\\player\\mini-player.js", "source_location": "L9", "weight": 1.0}, {"source": "f_youtube_2_0_src_content_features_player_mini_player_js", "target": "player_mini_player_getconfigkey", "relation": "contains", "confidence": "EXTRACTED", "source_file": "F:\\Youtube 2.0\\src\\content\\features\\player\\mini-player.js", "source_location": "L30", "weight": 1.0}, {"source": "f_youtube_2_0_src_content_features_player_mini_player_js", "target": "player_mini_player_enable", "relation": "contains", "confidence": "EXTRACTED", "source_file": "F:\\Youtube 2.0\\src\\content\\features\\player\\mini-player.js", "source_location": "L34", "weight": 1.0}, {"source": "f_youtube_2_0_src_content_features_player_mini_player_js", "target": "player_mini_player_disable", "relation": "contains", "confidence": "EXTRACTED", "source_file": "F:\\Youtube 2.0\\src\\content\\features\\player\\mini-player.js", "source_location": "L50", "weight": 1.0}, {"source": "f_youtube_2_0_src_content_features_player_mini_player_js", "target": "player_mini_player_checkminiplayerstate", "relation": "contains", "confidence": "EXTRACTED", "source_file": "F:\\Youtube 2.0\\src\\content\\features\\player\\mini-player.js", "source_location": "L66", "weight": 1.0}, {"source": "f_youtube_2_0_src_content_features_player_mini_player_js", "target": "player_mini_player_injectresizehandle", "relation": "contains", "confidence": "EXTRACTED", "source_file": "F:\\Youtube 2.0\\src\\content\\features\\player\\mini-player.js", "source_location": "L82", "weight": 1.0}, {"source": "f_youtube_2_0_src_content_features_player_mini_player_js", "target": "player_mini_player_ondragstart", "relation": "contains", "confidence": "EXTRACTED", "source_file": "F:\\Youtube 2.0\\src\\content\\features\\player\\mini-player.js", "source_location": "L113", "weight": 1.0}, {"source": "f_youtube_2_0_src_content_features_player_mini_player_js", "target": "player_mini_player_ondrag", "relation": "contains", "confidence": "EXTRACTED", "source_file": "F:\\Youtube 2.0\\src\\content\\features\\player\\mini-player.js", "source_location": "L132", "weight": 1.0}, {"source": "f_youtube_2_0_src_content_features_player_mini_player_js", "target": "player_mini_player_ondragend", "relation": "contains", "confidence": "EXTRACTED", "source_file": "F:\\Youtube 2.0\\src\\content\\features\\player\\mini-player.js", "source_location": "L154", "weight": 1.0}, {"source": "player_mini_player_enable", "target": "player_mini_player_checkminiplayerstate", "relation": "calls", "confidence": "EXTRACTED", "source_file": "F:\\Youtube 2.0\\src\\content\\features\\player\\mini-player.js", "source_location": "L44", "weight": 1.0}, {"source": "player_mini_player_checkminiplayerstate", "target": "player_mini_player_injectresizehandle", "relation": "calls", "confidence": "EXTRACTED", "source_file": "F:\\Youtube 2.0\\src\\content\\features\\player\\mini-player.js", "source_location": "L74", "weight": 1.0}], "raw_calls": [{"caller_nid": "player_mini_player_constructor", "callee": "super", "is_member_call": false, "source_file": "F:\\Youtube 2.0\\src\\content\\features\\player\\mini-player.js", "source_location": "L10"}, {"caller_nid": "player_mini_player_constructor", "callee": "bind", "is_member_call": true, "source_file": "F:\\Youtube 2.0\\src\\content\\features\\player\\mini-player.js", "source_location": "L24"}, {"caller_nid": "player_mini_player_constructor", "callee": "bind", "is_member_call": true, "source_file": "F:\\Youtube 2.0\\src\\content\\features\\player\\mini-player.js", "source_location": "L25"}, {"caller_nid": "player_mini_player_constructor", "callee": "bind", "is_member_call": true, "source_file": "F:\\Youtube 2.0\\src\\content\\features\\player\\mini-player.js", "source_location": "L26"}, {"caller_nid": "player_mini_player_constructor", "callee": "bind", "is_member_call": true, "source_file": "F:\\Youtube 2.0\\src\\content\\features\\player\\mini-player.js", "source_location": "L27"}, {"caller_nid": "player_mini_player_enable", "callee": "addListener", "is_member_call": true, "source_file": "F:\\Youtube 2.0\\src\\content\\features\\player\\mini-player.js", "source_location": "L39"}, {"caller_nid": "player_mini_player_enable", "callee": "addListener", "is_member_call": true, "source_file": "F:\\Youtube 2.0\\src\\content\\features\\player\\mini-player.js", "source_location": "L40"}, {"caller_nid": "player_mini_player_enable", "callee": "setInterval", "is_member_call": false, "source_file": "F:\\Youtube 2.0\\src\\content\\features\\player\\mini-player.js", "source_location": "L43"}, {"caller_nid": "player_mini_player_enable", "callee": "log", "is_member_call": true, "source_file": "F:\\Youtube 2.0\\src\\content\\features\\player\\mini-player.js", "source_location": "L46"}, {"caller_nid": "player_mini_player_disable", "callee": "clearInterval", "is_member_call": false, "source_file": "F:\\Youtube 2.0\\src\\content\\features\\player\\mini-player.js", "source_location": "L52"}, {"caller_nid": "player_mini_player_disable", "callee": "remove", "is_member_call": true, "source_file": "F:\\Youtube 2.0\\src\\content\\features\\player\\mini-player.js", "source_location": "L55"}, {"caller_nid": "player_mini_player_checkminiplayerstate", "callee": "querySelector", "is_member_call": true, "source_file": "F:\\Youtube 2.0\\src\\content\\features\\player\\mini-player.js", "source_location": "L70"}, {"caller_nid": "player_mini_player_checkminiplayerstate", "callee": "remove", "is_member_call": true, "source_file": "F:\\Youtube 2.0\\src\\content\\features\\player\\mini-player.js", "source_location": "L76"}, {"caller_nid": "player_mini_player_injectresizehandle", "callee": "createElement", "is_member_call": true, "source_file": "F:\\Youtube 2.0\\src\\content\\features\\player\\mini-player.js", "source_location": "L88"}, {"caller_nid": "player_mini_player_injectresizehandle", "callee": "addEventListener", "is_member_call": true, "source_file": "F:\\Youtube 2.0\\src\\content\\features\\player\\mini-player.js", "source_location": "L105"}, {"caller_nid": "player_mini_player_injectresizehandle", "callee": "addEventListener", "is_member_call": true, "source_file": "F:\\Youtube 2.0\\src\\content\\features\\player\\mini-player.js", "source_location": "L106"}, {"caller_nid": "player_mini_player_injectresizehandle", "callee": "addListener", "is_member_call": true, "source_file": "F:\\Youtube 2.0\\src\\content\\features\\player\\mini-player.js", "source_location": "L108"}, {"caller_nid": "player_mini_player_injectresizehandle", "callee": "appendChild", "is_member_call": true, "source_file": "F:\\Youtube 2.0\\src\\content\\features\\player\\mini-player.js", "source_location": "L110"}, {"caller_nid": "player_mini_player_ondragstart", "callee": "preventDefault", "is_member_call": true, "source_file": "F:\\Youtube 2.0\\src\\content\\features\\player\\mini-player.js", "source_location": "L115"}, {"caller_nid": "player_mini_player_ondragstart", "callee": "getBoundingClientRect", "is_member_call": true, "source_file": "F:\\Youtube 2.0\\src\\content\\features\\player\\mini-player.js", "source_location": "L121"}, {"caller_nid": "player_mini_player_ondragstart", "callee": "addEventListener", "is_member_call": true, "source_file": "F:\\Youtube 2.0\\src\\content\\features\\player\\mini-player.js", "source_location": "L125"}, {"caller_nid": "player_mini_player_ondragstart", "callee": "addEventListener", "is_member_call": true, "source_file": "F:\\Youtube 2.0\\src\\content\\features\\player\\mini-player.js", "source_location": "L126"}, {"caller_nid": "player_mini_player_ondrag", "callee": "max", "is_member_call": true, "source_file": "F:\\Youtube 2.0\\src\\content\\features\\player\\mini-player.js", "source_location": "L140"}, {"caller_nid": "player_mini_player_ondrag", "callee": "min", "is_member_call": true, "source_file": "F:\\Youtube 2.0\\src\\content\\features\\player\\mini-player.js", "source_location": "L140"}, {"caller_nid": "player_mini_player_ondrag", "callee": "querySelector", "is_member_call": true, "source_file": "F:\\Youtube 2.0\\src\\content\\features\\player\\mini-player.js", "source_location": "L147"}, {"caller_nid": "player_mini_player_ondragend", "callee": "removeEventListener", "is_member_call": true, "source_file": "F:\\Youtube 2.0\\src\\content\\features\\player\\mini-player.js", "source_location": "L156"}, {"caller_nid": "player_mini_player_ondragend", "callee": "removeEventListener", "is_member_call": true, "source_file": "F:\\Youtube 2.0\\src\\content\\features\\player\\mini-player.js", "source_location": "L157"}]}