{"nodes": [{"id": "f_youtube_2_0_src_content_features_player_wheel_controls_js", "label": "wheel-controls.js", "file_type": "code", "source_file": "F:\\Youtube 2.0\\src\\content\\features\\player\\wheel-controls.js", "source_location": "L1"}, {"id": "player_wheel_controls_constructor", "label": "constructor()", "file_type": "code", "source_file": "F:\\Youtube 2.0\\src\\content\\features\\player\\wheel-controls.js", "source_location": "L9"}, {"id": "player_wheel_controls_getconfigkey", "label": "getConfigKey()", "file_type": "code", "source_file": "F:\\Youtube 2.0\\src\\content\\features\\player\\wheel-controls.js", "source_location": "L16"}, {"id": "player_wheel_controls_enable", "label": "enable()", "file_type": "code", "source_file": "F:\\Youtube 2.0\\src\\content\\features\\player\\wheel-controls.js", "source_location": "L20"}, {"id": "player_wheel_controls_disable", "label": "disable()", "file_type": "code", "source_file": "F:\\Youtube 2.0\\src\\content\\features\\player\\wheel-controls.js", "source_location": "L31"}, {"id": "player_wheel_controls_getvideoelement", "label": "getVideoElement()", "file_type": "code", "source_file": "F:\\Youtube 2.0\\src\\content\\features\\player\\wheel-controls.js", "source_location": "L39"}, {"id": "player_wheel_controls_handlewheel", "label": "handleWheel()", "file_type": "code", "source_file": "F:\\Youtube 2.0\\src\\content\\features\\player\\wheel-controls.js", "source_location": "L44"}], "edges": [{"source": "f_youtube_2_0_src_content_features_player_wheel_controls_js", "target": "player_wheel_controls_constructor", "relation": "contains", "confidence": "EXTRACTED", "source_file": "F:\\Youtube 2.0\\src\\content\\features\\player\\wheel-controls.js", "source_location": "L9", "weight": 1.0}, {"source": "f_youtube_2_0_src_content_features_player_wheel_controls_js", "target": "player_wheel_controls_getconfigkey", "relation": "contains", "confidence": "EXTRACTED", "source_file": "F:\\Youtube 2.0\\src\\content\\features\\player\\wheel-controls.js", "source_location": "L16", "weight": 1.0}, {"source": "f_youtube_2_0_src_content_features_player_wheel_controls_js", "target": "player_wheel_controls_enable", "relation": "contains", "confidence": "EXTRACTED", "source_file": "F:\\Youtube 2.0\\src\\content\\features\\player\\wheel-controls.js", "source_location": "L20", "weight": 1.0}, {"source": "f_youtube_2_0_src_content_features_player_wheel_controls_js", "target": "player_wheel_controls_disable", "relation": "contains", "confidence": "EXTRACTED", "source_file": "F:\\Youtube 2.0\\src\\content\\features\\player\\wheel-controls.js", "source_location": "L31", "weight": 1.0}, {"source": "f_youtube_2_0_src_content_features_player_wheel_controls_js", "target": "player_wheel_controls_getvideoelement", "relation": "contains", "confidence": "EXTRACTED", "source_file": "F:\\Youtube 2.0\\src\\content\\features\\player\\wheel-controls.js", "source_location": "L39", "weight": 1.0}, {"source": "f_youtube_2_0_src_content_features_player_wheel_controls_js", "target": "player_wheel_controls_handlewheel", "relation": "contains", "confidence": "EXTRACTED", "source_file": "F:\\Youtube 2.0\\src\\content\\features\\player\\wheel-controls.js", "source_location": "L44", "weight": 1.0}, {"source": "player_wheel_controls_handlewheel", "target": "player_wheel_controls_getvideoelement", "relation": "calls", "confidence": "EXTRACTED", "source_file": "F:\\Youtube 2.0\\src\\content\\features\\player\\wheel-controls.js", "source_location": "L52", "weight": 1.0}], "raw_calls": [{"caller_nid": "player_wheel_controls_constructor", "callee": "super", "is_member_call": false, "source_file": "F:\\Youtube 2.0\\src\\content\\features\\player\\wheel-controls.js", "source_location": "L10"}, {"caller_nid": "player_wheel_controls_constructor", "callee": "bind", "is_member_call": true, "source_file": "F:\\Youtube 2.0\\src\\content\\features\\player\\wheel-controls.js", "source_location": "L13"}, {"caller_nid": "player_wheel_controls_enable", "callee": "waitForElement", "is_member_call": true, "source_file": "F:\\Youtube 2.0\\src\\content\\features\\player\\wheel-controls.js", "source_location": "L24"}, {"caller_nid": "player_wheel_controls_enable", "callee": "addEventListener", "is_member_call": true, "source_file": "F:\\Youtube 2.0\\src\\content\\features\\player\\wheel-controls.js", "source_location": "L27"}, {"caller_nid": "player_wheel_controls_disable", "callee": "removeEventListener", "is_member_call": true, "source_file": "F:\\Youtube 2.0\\src\\content\\features\\player\\wheel-controls.js", "source_location": "L34"}, {"caller_nid": "player_wheel_controls_getvideoelement", "callee": "querySelector", "is_member_call": true, "source_file": "F:\\Youtube 2.0\\src\\content\\features\\player\\wheel-controls.js", "source_location": "L40"}, {"caller_nid": "player_wheel_controls_handlewheel", "callee": "preventDefault", "is_member_call": true, "source_file": "F:\\Youtube 2.0\\src\\content\\features\\player\\wheel-controls.js", "source_location": "L56"}, {"caller_nid": "player_wheel_controls_handlewheel", "callee": "stopPropagation", "is_member_call": true, "source_file": "F:\\Youtube 2.0\\src\\content\\features\\player\\wheel-controls.js", "source_location": "L57"}, {"caller_nid": "player_wheel_controls_handlewheel", "callee": "max", "is_member_call": true, "source_file": "F:\\Youtube 2.0\\src\\content\\features\\player\\wheel-controls.js", "source_location": "L66"}, {"caller_nid": "player_wheel_controls_handlewheel", "callee": "min", "is_member_call": true, "source_file": "F:\\Youtube 2.0\\src\\content\\features\\player\\wheel-controls.js", "source_location": "L66"}, {"caller_nid": "player_wheel_controls_handlewheel", "callee": "round", "is_member_call": true, "source_file": "F:\\Youtube 2.0\\src\\content\\features\\player\\wheel-controls.js", "source_location": "L69"}, {"caller_nid": "player_wheel_controls_handlewheel", "callee": "createToast", "is_member_call": true, "source_file": "F:\\Youtube 2.0\\src\\content\\features\\player\\wheel-controls.js", "source_location": "L74"}, {"caller_nid": "player_wheel_controls_handlewheel", "callee": "max", "is_member_call": true, "source_file": "F:\\Youtube 2.0\\src\\content\\features\\player\\wheel-controls.js", "source_location": "L81"}, {"caller_nid": "player_wheel_controls_handlewheel", "callee": "min", "is_member_call": true, "source_file": "F:\\Youtube 2.0\\src\\content\\features\\player\\wheel-controls.js", "source_location": "L81"}, {"caller_nid": "player_wheel_controls_handlewheel", "callee": "createToast", "is_member_call": true, "source_file": "F:\\Youtube 2.0\\src\\content\\features\\player\\wheel-controls.js", "source_location": "L86"}, {"caller_nid": "player_wheel_controls_handlewheel", "callee": "round", "is_member_call": true, "source_file": "F:\\Youtube 2.0\\src\\content\\features\\player\\wheel-controls.js", "source_location": "L86"}]}