{"nodes":[{"id":"search_advanced_filter","label":"advanced-filter.js","file_type":"code","source_file":"F:\\Youtube 2.0\\src\\content\\features\\pages\\search\\advanced-filter.js","source_location":"L1"},{"id":"search_advanced_filter_getconfigkey","label":"getConfigKey()","file_type":"code","source_file":"F:\\Youtube 2.0\\src\\content\\features\\pages\\search\\advanced-filter.js","source_location":"L6"},{"id":"search_advanced_filter_constructor","label":"constructor()","file_type":"code","source_file":"F:\\Youtube 2.0\\src\\content\\features\\pages\\search\\advanced-filter.js","source_location":"L23"},{"id":"search_advanced_filter_run","label":"run()","file_type":"code","source_file":"F:\\Youtube 2.0\\src\\content\\features\\pages\\search\\advanced-filter.js","source_location":"L48"},{"id":"search_advanced_filter_init","label":"init()","file_type":"code","source_file":"F:\\Youtube 2.0\\src\\content\\features\\pages\\search\\advanced-filter.js","source_location":"L59"},{"id":"search_advanced_filter_disable","label":"disable()","file_type":"code","source_file":"F:\\Youtube 2.0\\src\\content\\features\\pages\\search\\advanced-filter.js","source_location":"L76"},{"id":"search_advanced_filter_createchipsbar","label":"_createChipsBar()","file_type":"code","source_file":"F:\\Youtube 2.0\\src\\content\\features\\pages\\search\\advanced-filter.js","source_location":"L85"},{"id":"search_advanced_filter_handlechipclick","label":"_handleChipClick()","file_type":"code","source_file":"F:\\Youtube 2.0\\src\\content\\features\\pages\\search\\advanced-filter.js","source_location":"L137"},{"id":"search_advanced_filter_updatechipsui","label":"_updateChipsUI()","file_type":"code","source_file":"F:\\Youtube 2.0\\src\\content\\features\\pages\\search\\advanced-filter.js","source_location":"L155"},{"id":"search_advanced_filter_apply","label":"apply()","file_type":"code","source_file":"F:\\Youtube 2.0\\src\\content\\features\\pages\\search\\advanced-filter.js","source_location":"L174"},{"id":"search_advanced_filter_checkcriteriastrict","label":"_checkCriteriaStrict()","file_type":"code","source_file":"F:\\Youtube 2.0\\src\\content\\features\\pages\\search\\advanced-filter.js","source_location":"L213"},{"id":"search_advanced_filter_getvideocards","label":"_getVideoCards()","file_type":"code","source_file":"F:\\Youtube 2.0\\src\\content\\features\\pages\\search\\advanced-filter.js","source_location":"L252"},{"id":"search_advanced_filter_parsevideodata","label":"_parseVideoData()","file_type":"code","source_file":"F:\\Youtube 2.0\\src\\content\\features\\pages\\search\\advanced-filter.js","source_location":"L262"},{"id":"search_advanced_filter_extracttitle","label":"_extractTitle()","file_type":"code","source_file":"F:\\Youtube 2.0\\src\\content\\features\\pages\\search\\advanced-filter.js","source_location":"L279"},{"id":"search_advanced_filter_extractduration","label":"_extractDuration()","file_type":"code","source_file":"F:\\Youtube 2.0\\src\\content\\features\\pages\\search\\advanced-filter.js","source_location":"L285"},{"id":"search_advanced_filter_parsedurationstring","label":"_parseDurationString()","file_type":"code","source_file":"F:\\Youtube 2.0\\src\\content\\features\\pages\\search\\advanced-filter.js","source_location":"L306"},{"id":"search_advanced_filter_extractuploadtime","label":"_extractUploadTime()","file_type":"code","source_file":"F:\\Youtube 2.0\\src\\content\\features\\pages\\search\\advanced-filter.js","source_location":"L323"},{"id":"search_advanced_filter_parseuploadbucket","label":"_parseUploadBucket()","file_type":"code","source_file":"F:\\Youtube 2.0\\src\\content\\features\\pages\\search\\advanced-filter.js","source_location":"L344"},{"id":"search_advanced_filter_extractsubscriptionstatus","label":"_extractSubscriptionStatus()","file_type":"code","source_file":"F:\\Youtube 2.0\\src\\content\\features\\pages\\search\\advanced-filter.js","source_location":"L361"},{"id":"search_advanced_filter_extractismix","label":"_extractIsMix()","file_type":"code","source_file":"F:\\Youtube 2.0\\src\\content\\features\\pages\\search\\advanced-filter.js","source_location":"L371"},{"id":"search_advanced_filter_extractisshort","label":"_extractIsShort()","file_type":"code","source_file":"F:\\Youtube 2.0\\src\\content\\features\\pages\\search\\advanced-filter.js","source_location":"L375"},{"id":"search_advanced_filter_updatestats","label":"_updateStats()","file_type":"code","source_file":"F:\\Youtube 2.0\\src\\content\\features\\pages\\search\\advanced-filter.js","source_location":"L379"}],"edges":[{"source":"search_advanced_filter","target":"search_advanced_filter_getconfigkey","relation":"contains","confidence":"EXTRACTED","source_file":"F:\\Youtube 2.0\\src\\content\\features\\pages\\search\\advanced-filter.js","source_location":"L6","weight":1},{"source":"search_advanced_filter","target":"search_advanced_filter_constructor","relation":"contains","confidence":"EXTRACTED","source_file":"F:\\Youtube 2.0\\src\\content\\features\\pages\\search\\advanced-filter.js","source_location":"L23","weight":1},{"source":"search_advanced_filter","target":"search_advanced_filter_run","relation":"contains","confidence":"EXTRACTED","source_file":"F:\\Youtube 2.0\\src\\content\\features\\pages\\search\\advanced-filter.js","source_location":"L48","weight":1},{"source":"search_advanced_filter","target":"search_advanced_filter_init","relation":"contains","confidence":"EXTRACTED","source_file":"F:\\Youtube 2.0\\src\\content\\features\\pages\\search\\advanced-filter.js","source_location":"L59","weight":1},{"source":"search_advanced_filter","target":"search_advanced_filter_disable","relation":"contains","confidence":"EXTRACTED","source_file":"F:\\Youtube 2.0\\src\\content\\features\\pages\\search\\advanced-filter.js","source_location":"L76","weight":1},{"source":"search_advanced_filter","target":"search_advanced_filter_createchipsbar","relation":"contains","confidence":"EXTRACTED","source_file":"F:\\Youtube 2.0\\src\\content\\features\\pages\\search\\advanced-filter.js","source_location":"L85","weight":1},{"source":"search_advanced_filter","target":"search_advanced_filter_handlechipclick","relation":"contains","confidence":"EXTRACTED","source_file":"F:\\Youtube 2.0\\src\\content\\features\\pages\\search\\advanced-filter.js","source_location":"L137","weight":1},{"source":"search_advanced_filter","target":"search_advanced_filter_updatechipsui","relation":"contains","confidence":"EXTRACTED","source_file":"F:\\Youtube 2.0\\src\\content\\features\\pages\\search\\advanced-filter.js","source_location":"L155","weight":1},{"source":"search_advanced_filter","target":"search_advanced_filter_apply","relation":"contains","confidence":"EXTRACTED","source_file":"F:\\Youtube 2.0\\src\\content\\features\\pages\\search\\advanced-filter.js","source_location":"L174","weight":1},{"source":"search_advanced_filter","target":"search_advanced_filter_checkcriteriastrict","relation":"contains","confidence":"EXTRACTED","source_file":"F:\\Youtube 2.0\\src\\content\\features\\pages\\search\\advanced-filter.js","source_location":"L213","weight":1},{"source":"search_advanced_filter","target":"search_advanced_filter_getvideocards","relation":"contains","confidence":"EXTRACTED","source_file":"F:\\Youtube 2.0\\src\\content\\features\\pages\\search\\advanced-filter.js","source_location":"L252","weight":1},{"source":"search_advanced_filter","target":"search_advanced_filter_parsevideodata","relation":"contains","confidence":"EXTRACTED","source_file":"F:\\Youtube 2.0\\src\\content\\features\\pages\\search\\advanced-filter.js","source_location":"L262","weight":1},{"source":"search_advanced_filter","target":"search_advanced_filter_extracttitle","relation":"contains","confidence":"EXTRACTED","source_file":"F:\\Youtube 2.0\\src\\content\\features\\pages\\search\\advanced-filter.js","source_location":"L279","weight":1},{"source":"search_advanced_filter","target":"search_advanced_filter_extractduration","relation":"contains","confidence":"EXTRACTED","source_file":"F:\\Youtube 2.0\\src\\content\\features\\pages\\search\\advanced-filter.js","source_location":"L285","weight":1},{"source":"search_advanced_filter","target":"search_advanced_filter_parsedurationstring","relation":"contains","confidence":"EXTRACTED","source_file":"F:\\Youtube 2.0\\src\\content\\features\\pages\\search\\advanced-filter.js","source_location":"L306","weight":1},{"source":"search_advanced_filter","target":"search_advanced_filter_extractuploadtime","relation":"contains","confidence":"EXTRACTED","source_file":"F:\\Youtube 2.0\\src\\content\\features\\pages\\search\\advanced-filter.js","source_location":"L323","weight":1},{"source":"search_advanced_filter","target":"search_advanced_filter_parseuploadbucket","relation":"contains","confidence":"EXTRACTED","source_file":"F:\\Youtube 2.0\\src\\content\\features\\pages\\search\\advanced-filter.js","source_location":"L344","weight":1},{"source":"search_advanced_filter","target":"search_advanced_filter_extractsubscriptionstatus","relation":"contains","confidence":"EXTRACTED","source_file":"F:\\Youtube 2.0\\src\\content\\features\\pages\\search\\advanced-filter.js","source_location":"L361","weight":1},{"source":"search_advanced_filter","target":"search_advanced_filter_extractismix","relation":"contains","confidence":"EXTRACTED","source_file":"F:\\Youtube 2.0\\src\\content\\features\\pages\\search\\advanced-filter.js","source_location":"L371","weight":1},{"source":"search_advanced_filter","target":"search_advanced_filter_extractisshort","relation":"contains","confidence":"EXTRACTED","source_file":"F:\\Youtube 2.0\\src\\content\\features\\pages\\search\\advanced-filter.js","source_location":"L375","weight":1},{"source":"search_advanced_filter","target":"search_advanced_filter_updatestats","relation":"contains","confidence":"EXTRACTED","source_file":"F:\\Youtube 2.0\\src\\content\\features\\pages\\search\\advanced-filter.js","source_location":"L379","weight":1},{"source":"search_advanced_filter_run","target":"search_advanced_filter_init","relation":"calls","confidence":"EXTRACTED","source_file":"F:\\Youtube 2.0\\src\\content\\features\\pages\\search\\advanced-filter.js","source_location":"L53","weight":1},{"source":"search_advanced_filter_run","target":"search_advanced_filter_disable","relation":"calls","confidence":"EXTRACTED","source_file":"F:\\Youtube 2.0\\src\\content\\features\\pages\\search\\advanced-filter.js","source_location":"L55","weight":1},{"source":"search_advanced_filter_init","target":"search_advanced_filter_createchipsbar","relation":"calls","confidence":"EXTRACTED","source_file":"F:\\Youtube 2.0\\src\\content\\features\\pages\\search\\advanced-filter.js","source_location":"L63","weight":1},{"source":"search_advanced_filter_handlechipclick","target":"search_advanced_filter_updatechipsui","relation":"calls","confidence":"EXTRACTED","source_file":"F:\\Youtube 2.0\\src\\content\\features\\pages\\search\\advanced-filter.js","source_location":"L151","weight":1},{"source":"search_advanced_filter_handlechipclick","target":"search_advanced_filter_apply","relation":"calls","confidence":"EXTRACTED","source_file":"F:\\Youtube 2.0\\src\\content\\features\\pages\\search\\advanced-filter.js","source_location":"L152","weight":1},{"source":"search_advanced_filter_apply","target":"search_advanced_filter_getvideocards","relation":"calls","confidence":"EXTRACTED","source_file":"F:\\Youtube 2.0\\src\\content\\features\\pages\\search\\advanced-filter.js","source_location":"L175","weight":1},{"source":"search_advanced_filter_apply","target":"search_advanced_filter_updatestats","relation":"calls","confidence":"EXTRACTED","source_file":"F:\\Youtube 2.0\\src\\content\\features\\pages\\search\\advanced-filter.js","source_location":"L209","weight":1},{"source":"search_advanced_filter_parsevideodata","target":"search_advanced_filter_extracttitle","relation":"calls","confidence":"EXTRACTED","source_file":"F:\\Youtube 2.0\\src\\content\\features\\pages\\search\\advanced-filter.js","source_location":"L265","weight":1},{"source":"search_advanced_filter_parsevideodata","target":"search_advanced_filter_extractduration","relation":"calls","confidence":"EXTRACTED","source_file":"F:\\Youtube 2.0\\src\\content\\features\\pages\\search\\advanced-filter.js","source_location":"L266","weight":1},{"source":"search_advanced_filter_parsevideodata","target":"search_advanced_filter_extractuploadtime","relation":"calls","confidence":"EXTRACTED","source_file":"F:\\Youtube 2.0\\src\\content\\features\\pages\\search\\advanced-filter.js","source_location":"L267","weight":1},{"source":"search_advanced_filter_parsevideodata","target":"search_advanced_filter_extractsubscriptionstatus","relation":"calls","confidence":"EXTRACTED","source_file":"F:\\Youtube 2.0\\src\\content\\features\\pages\\search\\advanced-filter.js","source_location":"L268","weight":1},{"source":"search_advanced_filter_parsevideodata","target":"search_advanced_filter_extractismix","relation":"calls","confidence":"EXTRACTED","source_file":"F:\\Youtube 2.0\\src\\content\\features\\pages\\search\\advanced-filter.js","source_location":"L269","weight":1},{"source":"search_advanced_filter_parsevideodata","target":"search_advanced_filter_extractisshort","relation":"calls","confidence":"EXTRACTED","source_file":"F:\\Youtube 2.0\\src\\content\\features\\pages\\search\\advanced-filter.js","source_location":"L270","weight":1},{"source":"search_advanced_filter_extractduration","target":"search_advanced_filter_parsedurationstring","relation":"calls","confidence":"EXTRACTED","source_file":"F:\\Youtube 2.0\\src\\content\\features\\pages\\search\\advanced-filter.js","source_location":"L303","weight":1},{"source":"search_advanced_filter_extractuploadtime","target":"search_advanced_filter_parseuploadbucket","relation":"calls","confidence":"EXTRACTED","source_file":"F:\\Youtube 2.0\\src\\content\\features\\pages\\search\\advanced-filter.js","source_location":"L341","weight":1}]}