{"nodes":[{"id":"content_feature_manager","label":"feature-manager.js","file_type":"code","source_file":"F:\\Youtube 2.0\\src\\content\\feature-manager.js","source_location":"L1"},{"id":"content_feature_manager_constructor","label":"constructor()","file_type":"code","source_file":"F:\\Youtube 2.0\\src\\content\\feature-manager.js","source_location":"L12"},{"id":"content_feature_manager_init","label":"init()","file_type":"code","source_file":"F:\\Youtube 2.0\\src\\content\\feature-manager.js","source_location":"L31"},{"id":"content_feature_manager_setuplifecyclebindings","label":"setupLifecycleBindings()","file_type":"code","source_file":"F:\\Youtube 2.0\\src\\content\\feature-manager.js","source_location":"L55"},{"id":"content_feature_manager_reseterrors","label":"resetErrors()","file_type":"code","source_file":"F:\\Youtube 2.0\\src\\content\\feature-manager.js","source_location":"L78"},{"id":"content_feature_manager_instantiatefeatures","label":"instantiateFeatures()","file_type":"code","source_file":"F:\\Youtube 2.0\\src\\content\\feature-manager.js","source_location":"L86"},{"id":"content_feature_manager_getfeature","label":"getFeature()","file_type":"code","source_file":"F:\\Youtube 2.0\\src\\content\\feature-manager.js","source_location":"L141"},{"id":"content_feature_manager_applyfeatures","label":"applyFeatures()","file_type":"code","source_file":"F:\\Youtube 2.0\\src\\content\\feature-manager.js","source_location":"L150"},{"id":"content_feature_manager_saferun","label":"safeRun()","file_type":"code","source_file":"F:\\Youtube 2.0\\src\\content\\feature-manager.js","source_location":"L194"},{"id":"content_feature_manager_domsweep","label":"_domSweep()","file_type":"code","source_file":"F:\\Youtube 2.0\\src\\content\\feature-manager.js","source_location":"L246"},{"id":"content_feature_manager_disableall","label":"disableAll()","file_type":"code","source_file":"F:\\Youtube 2.0\\src\\content\\feature-manager.js","source_location":"L269"}],"edges":[{"source":"content_feature_manager","target":"content_feature_manager_constructor","relation":"contains","confidence":"EXTRACTED","source_file":"F:\\Youtube 2.0\\src\\content\\feature-manager.js","source_location":"L12","weight":1},{"source":"content_feature_manager","target":"content_feature_manager_init","relation":"contains","confidence":"EXTRACTED","source_file":"F:\\Youtube 2.0\\src\\content\\feature-manager.js","source_location":"L31","weight":1},{"source":"content_feature_manager","target":"content_feature_manager_setuplifecyclebindings","relation":"contains","confidence":"EXTRACTED","source_file":"F:\\Youtube 2.0\\src\\content\\feature-manager.js","source_location":"L55","weight":1},{"source":"content_feature_manager","target":"content_feature_manager_reseterrors","relation":"contains","confidence":"EXTRACTED","source_file":"F:\\Youtube 2.0\\src\\content\\feature-manager.js","source_location":"L78","weight":1},{"source":"content_feature_manager","target":"content_feature_manager_instantiatefeatures","relation":"contains","confidence":"EXTRACTED","source_file":"F:\\Youtube 2.0\\src\\content\\feature-manager.js","source_location":"L86","weight":1},{"source":"content_feature_manager","target":"content_feature_manager_getfeature","relation":"contains","confidence":"EXTRACTED","source_file":"F:\\Youtube 2.0\\src\\content\\feature-manager.js","source_location":"L141","weight":1},{"source":"content_feature_manager","target":"content_feature_manager_applyfeatures","relation":"contains","confidence":"EXTRACTED","source_file":"F:\\Youtube 2.0\\src\\content\\feature-manager.js","source_location":"L150","weight":1},{"source":"content_feature_manager","target":"content_feature_manager_saferun","relation":"contains","confidence":"EXTRACTED","source_file":"F:\\Youtube 2.0\\src\\content\\feature-manager.js","source_location":"L194","weight":1},{"source":"content_feature_manager","target":"content_feature_manager_domsweep","relation":"contains","confidence":"EXTRACTED","source_file":"F:\\Youtube 2.0\\src\\content\\feature-manager.js","source_location":"L246","weight":1},{"source":"content_feature_manager","target":"content_feature_manager_disableall","relation":"contains","confidence":"EXTRACTED","source_file":"F:\\Youtube 2.0\\src\\content\\feature-manager.js","source_location":"L269","weight":1},{"source":"content_feature_manager_init","target":"content_feature_manager_reseterrors","relation":"calls","confidence":"EXTRACTED","source_file":"F:\\Youtube 2.0\\src\\content\\feature-manager.js","source_location":"L39","weight":1},{"source":"content_feature_manager_init","target":"content_feature_manager_instantiatefeatures","relation":"calls","confidence":"EXTRACTED","source_file":"F:\\Youtube 2.0\\src\\content\\feature-manager.js","source_location":"L44","weight":1},{"source":"content_feature_manager_init","target":"content_feature_manager_setuplifecyclebindings","relation":"calls","confidence":"EXTRACTED","source_file":"F:\\Youtube 2.0\\src\\content\\feature-manager.js","source_location":"L46","weight":1},{"source":"content_feature_manager_init","target":"content_feature_manager_applyfeatures","relation":"calls","confidence":"EXTRACTED","source_file":"F:\\Youtube 2.0\\src\\content\\feature-manager.js","source_location":"L49","weight":1},{"source":"content_feature_manager_saferun","target":"content_feature_manager_getfeature","relation":"calls","confidence":"EXTRACTED","source_file":"F:\\Youtube 2.0\\src\\content\\feature-manager.js","source_location":"L216","weight":1},{"source":"content_feature_manager_saferun","target":"content_feature_manager_domsweep","relation":"calls","confidence":"EXTRACTED","source_file":"F:\\Youtube 2.0\\src\\content\\feature-manager.js","source_location":"L229","weight":1}]}